clamfig/__init__.py
clamfig/base.py
clamfig-0.1.3.dist-info/METADATA
clamfig-0.1.3.dist-info/WHEEL
clamfig-0.1.3.dist-info/top_level.txt
clamfig-0.1.3.dist-info/RECORD
