Metadata-Version: 2.1
Name: clamfig
Version: 0.1.3
Summary: Serialization/Deserialization for dataclasses
Home-page: https://github.com/pydefi/clamfig
Author: PyDefi Development Team
Author-email: clamdad+pydefi@protonmail.com
License: MIT
Keywords: dataclasses,json,serialize,deserialize,config file
Platform: UNKNOWN
Classifier: Development Status :: 3 - Alpha
Classifier: Intended Audience :: Developers
Classifier: Topic :: Office/Business :: Financial
Classifier: License :: OSI Approved :: BSD License
Classifier: Programming Language :: Python :: 3.8
Classifier: Programming Language :: Python :: 3.9
Requires-Python: >=3.8
Requires-Dist: pyyaml
